{
  "title": "01. ОНА БУДЕТ УЧИТЕЛЬНИЦЕЙ",
  "fullText": "Наташа жила в небольшом городе на севере страны. Отец Наташи был инженером-строителем, а мама — учительницей. Старший брат Наташи недавно окончил московский институт и вернулся в родной город. Теперь он инженер-строитель и работает вместе с отцом. Наташа долго не могла решить, кем она будет, когда окончит школу. Она думала, что тоже может стать инженером и вместе с отцом и братом будет строить свой город, который она очень любит. Но профессия мамы тоже нравилась Наташе. В школе, где училась Наташа, её мама была учительницей русского языка и литературы. Уроки мамы были очень интересными. Мама учила своих учеников любить литературу и родной язык. Дети делали на уроках доклады о писателях, о книгах, которые они прочитали и которые им понравились. Многие ученики мамы хотели стать преподавателями. И только Наташа не могла решить, кем стать. Однажды, когда Наташа училась в десятом классе, сильно заболела её подруга. Четыре месяца она не ходила в школу. И очень часто, сначала в больницу, а потом домой Наташа приходила к своей подруге. Она занималась с подругой историей, математикой, русским языком, физикой, химией. Учителя составили специальный план для больной девушки и давали ей специальные задания. Все хотели помочь ей, но больше всех помогала Наташа. Подруга называла Наташу «моя учительница». Пришла весна. Нужно было сдавать экзамены. Врачи уже разрешили подруге Наташи ходить в школу. Девушки вместе готовились к экзаменам. Наташа была очень рада, когда её подруга сдала все экзамены. И тогда Наташа поняла, кем она хочет стать — учительницей и только учительницей. Наташа решила поехать в Москву, чтобы поступить в педагогический институт. В Москве она хорошо сдала все экзамены и стала студенткой. Сейчас она учится на втором курсе и мечтает вернуться в родной город, в свою школу, где она хочет, как и её мама, учить детей.",
  "words": [
    {
      "word": "она",
      "translation": "cô ấy"
    },
    {
      "word": "будет",
      "translation": "sẽ là"
    },
    {
      "word": "учительницей",
      "translation": "giáo viên (nữ)"
    },
    {
      "word": "жила",
      "translation": "đã sống"
    },
    {
      "word": "небольшом",
      "translation": "nhỏ"
    },
    {
      "word": "городе",
      "translation": "thành phố"
    },
    {
      "word": "севере",
      "translation": "phương bắc"
    },
    {
      "word": "страны",
      "translation": "đất nước"
    },
    {
      "word": "отец",
      "translation": "bố"
    },
    {
      "word": "инженером-строителем",
      "translation": "kỹ sư xây dựng"
    },
    {
      "word": "мама",
      "translation": "mẹ"
    },
    {
      "word": "старший",
      "translation": "lớn"
    },
    {
      "word": "брат",
      "translation": "anh trai"
    },
    {
      "word": "недавно",
      "translation": "gần đây"
    },
    {
      "word": "окончил",
      "translation": "tốt nghiệp"
    },
    {
      "word": "институт",
      "translation": "học viện"
    },
    {
      "word": "вернулся",
      "translation": "đã trở về"
    },
    {
      "word": "родной",
      "translation": "quê hương/ruột thịt"
    },
    {
      "word": "теперь",
      "translation": "bây giờ"
    },
    {
      "word": "работает",
      "translation": "làm việc"
    },
    {
      "word": "вместе",
      "translation": "cùng nhau"
    },
    {
      "word": "долго",
      "translation": "lâu"
    },
    {
      "word": "решить",
      "translation": "quyết định"
    },
    {
      "word": "школу",
      "translation": "trường học"
    },
    {
      "word": "думала",
      "translation": "đã nghĩ"
    },
    {
      "word": "может",
      "translation": "có thể"
    },
    {
      "word": "стать",
      "translation": "trở thành"
    },
    {
      "word": "строить",
      "translation": "xây dựng"
    },
    {
      "word": "любит",
      "translation": "yêu"
    },
    {
      "word": "профессия",
      "translation": "nghề nghiệp"
    },
    {
      "word": "нравилась",
      "translation": "đã thích"
    },
    {
      "word": "училась",
      "translation": "đã học"
    },
    {
      "word": "русского",
      "translation": "tiếng Nga"
    },
    {
      "word": "языка",
      "translation": "ngôn ngữ"
    },
    {
      "word": "литературы",
      "translation": "văn học"
    },
    {
      "word": "уроки",
      "translation": "các bài học"
    },
    {
      "word": "интересными",
      "translation": "thú vị"
    },
    {
      "word": "учеников",
      "translation": "học sinh"
    },
    {
      "word": "дети",
      "translation": "trẻ em"
    },
    {
      "word": "доклады",
      "translation": "báo cáo"
    },
    {
      "word": "писателях",
      "translation": "các nhà văn"
    },
    {
      "word": "книгах",
      "translation": "các cuốn sách"
    },
    {
      "word": "хотели",
      "translation": "đã muốn"
    },
    {
      "word": "однажды",
      "translation": "một ngày nọ"
    },
    {
      "word": "классе",
      "translation": "lớp học"
    },
    {
      "word": "заболела",
      "translation": "đã bị ốm"
    },
    {
      "word": "подруга",
      "translation": "bạn gái"
    },
    {
      "word": "месяца",
      "translation": "tháng"
    },
    {
      "word": "больницу",
      "translation": "bệnh viện"
    },
    {
      "word": "домой",
      "translation": "về nhà"
    },
    {
      "word": "занималась",
      "translation": "đã học/ôn tập"
    },
    {
      "word": "историей",
      "translation": "lịch sử"
    },
    {
      "word": "математикой",
      "translation": "toán học"
    },
    {
      "word": "физикой",
      "translation": "vật lý"
    },
    {
      "word": "химией",
      "translation": "hóa học"
    },
    {
      "word": "план",
      "translation": "kế hoạch"
    },
    {
      "word": "задания",
      "translation": "bài tập"
    },
    {
      "word": "помочь",
      "translation": "giúp đỡ"
    },
    {
      "word": "весна",
      "translation": "mùa xuân"
    },
    {
      "word": "экзамены",
      "translation": "kỳ thi"
    },
    {
      "word": "врачи",
      "translation": "bác sĩ"
    },
    {
      "word": "разрешили",
      "translation": "đã cho phép"
    },
    {
      "word": "готовились",
      "translation": "đã chuẩn bị"
    },
    {
      "word": "рада",
      "translation": "vui mừng"
    },
    {
      "word": "поняла",
      "translation": "đã hiểu/nhận ra"
    },
    {
      "word": "хочет",
      "translation": "muốn"
    },
    {
      "word": "поехать",
      "translation": "đi đến"
    },
    {
      "word": "педагогический",
      "translation": "sư phạm"
    },
    {
      "word": "студенткой",
      "translation": "sinh viên (nữ)"
    },
    {
      "word": "учится",
      "translation": "đang học"
    },
    {
      "word": "курсе",
      "translation": "khóa học/năm học"
    },
    {
      "word": "мечтает",
      "translation": "mơ ước"
    }
  ]
}